UtimateTestingProjectWithUnexpectedName/__init__.py
UtimateTestingProjectWithUnexpectedName/functions.py
UtimateTestingProjectWithUnexpectedName-0.0.1.dist-info/METADATA
UtimateTestingProjectWithUnexpectedName-0.0.1.dist-info/WHEEL
UtimateTestingProjectWithUnexpectedName-0.0.1.dist-info/top_level.txt
UtimateTestingProjectWithUnexpectedName-0.0.1.dist-info/RECORD
